{
  "container_1": {
    "id": "1",
    "name": "container 1",
    "cpu": 90,
    "mem": 60,
    "layers": [
      "1",
      "12",
      "123",
      "1234",
      "12345"
    ],
    "created": "Mon Jul 18 2016 12:33:00 GMT+0300 (IDT)"
  },
  "container_2": {
    "id": "2",
    "name": "container 2",
    "cpu": 80,
    "mem": 50,
    "layers": [
      "1",
      "12",
      "123",
      "1234",
      "12345"
    ],
    "created": "Mon Sep 13 1994 12:33:00 GMT+0300 (IDT)"
  },
  "container_3": {
    "id": "3",
    "name": "container 3",
    "cpu": 70,
    "mem": 40,
    "layers": [
      "1",
      "12",
      "123",
      "1234",
      "12345"
    ],
    "created": "Mon Jul 18 2016 10:50:00 GMT+0300 (IDT)"
  },
  "container_4": {
    "id": "4",
    "name": "container 4",
    "cpu": 60,
    "mem": 30,
    "layers": [
      "1",
      "12",
      "123",
      "1234",
      "12345"
    ],
    "created": "Mon Jul 18 2016 10:00:00 GMT+0300 (IDT)"
  },
  "container_5": {
    "id": "5",
    "name": "container 5",
    "cpu": 50,
    "mem": 20,
    "layers": [
      "1",
      "12",
      "123",
      "1234",
      "12345"
    ],
    "created": "Mon Jul 18 2016 10:33:00 GMT+0300 (IDT)"
  }
}